algo_beast_cli/__init__.py
algo_beast_cli/cmd/__init__.py
algo_beast_cli/cmd/boot.py
algo_beast_cli/cmd/initializer.py
algo_beast_cli/cmd/auth/default.json
algo_beast_cli/cmd/auth/main.json
algo_beast_cli/cmd/commands/__init__.py
algo_beast_cli/cmd/commands/create_project.py
algo_beast_cli/cmd/commands/init.py
algo_beast_cli/cmd/commands/pull.py
algo_beast_cli/cmd/commands/run.py
algo_beast_cli/cmd/protocols/__init__.py
algo_beast_cli/cmd/protocols/initializer.py
algo_beast_cli/cmd/stubs/.algo-beast/config.json
algo_beast_cli-0.1.8.dist-info/LICENSE
algo_beast_cli-0.1.8.dist-info/METADATA
algo_beast_cli-0.1.8.dist-info/WHEEL
algo_beast_cli-0.1.8.dist-info/entry_points.txt
algo_beast_cli-0.1.8.dist-info/top_level.txt
algo_beast_cli-0.1.8.dist-info/RECORD
