Metadata-Version: 2.1
Name: algo-beast-cli
Version: 0.1.8
Summary: Fyers Api Builder
Home-page: https://github.com/krunaldodiya/algo-beast-cli
Author: Krunal Dodiya
Author-email: kunal.dodiya1@gmail.com
Classifier: Programming Language :: Python :: 3
Classifier: Operating System :: OS Independent
License-File: LICENSE
Requires-Dist: algo-beast-protocols
Requires-Dist: certifi
Requires-Dist: charset-normalizer
Requires-Dist: click
Requires-Dist: colorama
Requires-Dist: idna
Requires-Dist: pwinput
Requires-Dist: requests
Requires-Dist: urllib3
